{
  "db_name": "PostgreSQL",
  "query": "SELECT id AS \"id!: Uuid\",\n                      workspace_id AS \"workspace_id!: Uuid\",\n                      executor,\n                      created_at AS \"created_at!: DateTime<Utc>\",\n                      updated_at AS \"updated_at!: DateTime<Utc>\"\n               FROM sessions\n               WHERE workspace_id = $1\n               ORDER BY created_at DESC\n               LIMIT 1",
  "describe": {
    "columns": [
      {
        "ordinal": 0,
        "name": "id!: Uuid",
        "type_info": "Uuid"
      },
      {
        "ordinal": 1,
        "name": "workspace_id!: Uuid",
        "type_info": "Uuid"
      },
      {
        "ordinal": 2,
        "name": "executor",
        "type_info": "Text"
      },
      {
        "ordinal": 3,
        "name": "created_at!: DateTime<Utc>",
        "type_info": "Timestamptz"
      },
      {
        "ordinal": 4,
        "name": "updated_at!: DateTime<Utc>",
        "type_info": "Timestamptz"
      }
    ],
    "parameters": {
      "Left": [
        "Uuid"
      ]
    },
    "nullable": [
      false,
      false,
      true,
      false,
      false
    ]
  },
  "hash": "5a8d67e33c564f02faef85a19503f204332b8353974718c96f23b2942c1fb142"
}
