{
  "db_name": "SQLite",
  "query": "SELECT ar.id as \"id!: Uuid\",\n                      ar.project_id as \"project_id!: Uuid\",\n                      ar.column_id as \"column_id!: Uuid\",\n                      kc.name as \"column_name!\",\n                      ar.trigger_type,\n                      ar.action_type,\n                      ar.action_config,\n                      ar.enabled as \"enabled!: bool\",\n                      ar.priority as \"priority!: i32\",\n                      ar.name,\n                      ar.created_at as \"created_at!: DateTime<Utc>\",\n                      ar.updated_at as \"updated_at!: DateTime<Utc>\"\n               FROM automation_rules ar\n               JOIN kanban_columns kc ON kc.id = ar.column_id\n               WHERE ar.project_id = $1\n               ORDER BY ar.priority ASC",
  "describe": {
    "columns": [
      {
        "name": "id!: Uuid",
        "ordinal": 0,
        "type_info": "Blob"
      },
      {
        "name": "project_id!: Uuid",
        "ordinal": 1,
        "type_info": "Blob"
      },
      {
        "name": "column_id!: Uuid",
        "ordinal": 2,
        "type_info": "Blob"
      },
      {
        "name": "column_name!",
        "ordinal": 3,
        "type_info": "Text"
      },
      {
        "name": "trigger_type",
        "ordinal": 4,
        "type_info": "Text"
      },
      {
        "name": "action_type",
        "ordinal": 5,
        "type_info": "Text"
      },
      {
        "name": "action_config",
        "ordinal": 6,
        "type_info": "Text"
      },
      {
        "name": "enabled!: bool",
        "ordinal": 7,
        "type_info": "Integer"
      },
      {
        "name": "priority!: i32",
        "ordinal": 8,
        "type_info": "Integer"
      },
      {
        "name": "name",
        "ordinal": 9,
        "type_info": "Text"
      },
      {
        "name": "created_at!: DateTime<Utc>",
        "ordinal": 10,
        "type_info": "Text"
      },
      {
        "name": "updated_at!: DateTime<Utc>",
        "ordinal": 11,
        "type_info": "Text"
      }
    ],
    "parameters": {
      "Right": 1
    },
    "nullable": [
      true,
      false,
      false,
      false,
      false,
      false,
      false,
      false,
      false,
      true,
      false,
      false
    ]
  },
  "hash": "c2e24649443bb78db923747b624dbcb51b563058d5edaeb5c2dda002d2632c58"
}
